<?xml version="1.0" encoding="utf-8" ?>
<dwsync>
<file name="Daecca-Bold.css" server="ftp.fxprodesign.co.uk//htdocs/" local="132297299992889209" remote="132297300000000000" Dst="1" />
<file name="Daecca-Bold.eot" server="ftp.fxprodesign.co.uk//htdocs/" local="132297299993318045" remote="132297300000000000" Dst="1" />
<file name="Daecca-Bold.ttf" server="ftp.fxprodesign.co.uk//htdocs/" local="132297299994365258" remote="132297300000000000" Dst="1" />
<file name="Daecca-Bold.html" server="ftp.fxprodesign.co.uk//htdocs/" local="132297299993627514" remote="132297300000000000" Dst="1" />
<file name="Daecca-Bold.svg" server="ftp.fxprodesign.co.uk//htdocs/" local="132297299994026176" remote="132297300000000000" Dst="1" />
<file name="Daecca-Bold.woff" server="ftp.fxprodesign.co.uk//htdocs/" local="132297299994634819" remote="132297300000000000" Dst="1" />
<file name="Daecca-Outline.css" server="ftp.fxprodesign.co.uk//htdocs/" local="132297299994963802" remote="132297300000000000" Dst="1" />
<file name="Daecca-Outline.eot" server="ftp.fxprodesign.co.uk//htdocs/" local="132297299995303035" remote="132297300000000000" Dst="1" />
<file name="Daecca-Outline.html" server="ftp.fxprodesign.co.uk//htdocs/" local="132297299995611917" remote="132297300000000000" Dst="1" />
<file name="Daecca-Outline.ttf" server="ftp.fxprodesign.co.uk//htdocs/" local="132297299996379884" remote="132297300000000000" Dst="1" />
<file name="Daecca-Outline.svg" server="ftp.fxprodesign.co.uk//htdocs/" local="132297299996040770" remote="132297300000000000" Dst="1" />
<file name="Daecca-Outline.woff" server="ftp.fxprodesign.co.uk//htdocs/" local="132297299996639173" remote="132297300000000000" Dst="1" />
<file name="Daecca-Regular.css" server="ftp.fxprodesign.co.uk//htdocs/" local="132297299996948630" remote="132297300000000000" Dst="1" />
<file name="Daecca-Regular.eot" server="ftp.fxprodesign.co.uk//htdocs/" local="132297299997287436" remote="132297300000000000" Dst="1" />
<file name="Daecca-Regular.html" server="ftp.fxprodesign.co.uk//htdocs/" local="132297299998136060" remote="132297300000000000" Dst="1" />
<file name="Daecca-Regular.ttf" server="ftp.fxprodesign.co.uk//htdocs/" local="132297299999203211" remote="132297300000000000" Dst="1" />
<file name="Daecca-Regular.woff" server="ftp.fxprodesign.co.uk//htdocs/" local="132297299999961176" remote="132297300000000000" Dst="1" />
<file name="Daecca-Regular.svg" server="ftp.fxprodesign.co.uk//htdocs/" local="132297299998794298" remote="132297300000000000" Dst="1" />
<file name="Daecca-Round.css" server="ftp.fxprodesign.co.uk//htdocs/" local="132297300000409972" remote="132297300000000000" Dst="1" />
<file name="Daecca-Round.eot" server="ftp.fxprodesign.co.uk//htdocs/" local="132297300000729131" remote="132297300000000000" Dst="1" />
<file name="Daecca-Round.html" server="ftp.fxprodesign.co.uk//htdocs/" local="132297300001098140" remote="132297300000000000" Dst="1" />
<file name="Daecca-Round.ttf" server="ftp.fxprodesign.co.uk//htdocs/" local="132297300001915968" remote="132297300000000000" Dst="1" />
<file name="Daecca-Round.svg" server="ftp.fxprodesign.co.uk//htdocs/" local="132297300001566883" remote="132297300000000000" Dst="1" />
<file name="Daecca-Round.woff" server="ftp.fxprodesign.co.uk//htdocs/" local="132297300002185243" remote="132297300000000000" Dst="1" />
<file name="Daecca-Bold.eot" server="ftp.fxprodesign.co.uk//htdocs/classroom/" local="132297299993318045" remote="132366771600000000" Dst="2" />
<file name="Daecca-Bold.html" server="ftp.fxprodesign.co.uk//htdocs/classroom/" local="132297299993627514" remote="132366771600000000" Dst="2" />
<file name="Daecca-Bold.css" server="ftp.fxprodesign.co.uk//htdocs/classroom/" local="132297299992889209" remote="132366771600000000" Dst="2" />
<file name="Daecca-Bold.ttf" server="ftp.fxprodesign.co.uk//htdocs/classroom/" local="132297299994365258" remote="132366771600000000" Dst="2" />
<file name="Daecca-Bold.woff" server="ftp.fxprodesign.co.uk//htdocs/classroom/" local="132297299994634819" remote="132366771600000000" Dst="2" />
<file name="Daecca-Bold.svg" server="ftp.fxprodesign.co.uk//htdocs/classroom/" local="132297299994026176" remote="132366771600000000" Dst="2" />
<file name="Daecca-Outline.css" server="ftp.fxprodesign.co.uk//htdocs/classroom/" local="132297299994963802" remote="132366771600000000" Dst="2" />
<file name="Daecca-Outline.eot" server="ftp.fxprodesign.co.uk//htdocs/classroom/" local="132297299995303035" remote="132366771600000000" Dst="2" />
<file name="Daecca-Outline.html" server="ftp.fxprodesign.co.uk//htdocs/classroom/" local="132297299995611917" remote="132366771600000000" Dst="2" />
<file name="Daecca-Outline.woff" server="ftp.fxprodesign.co.uk//htdocs/classroom/" local="132297299996639173" remote="132366771600000000" Dst="2" />
<file name="Daecca-Outline.ttf" server="ftp.fxprodesign.co.uk//htdocs/classroom/" local="132297299996379884" remote="132366771600000000" Dst="2" />
<file name="Daecca-Outline.svg" server="ftp.fxprodesign.co.uk//htdocs/classroom/" local="132297299996040770" remote="132366771600000000" Dst="2" />
<file name="Daecca-Regular.eot" server="ftp.fxprodesign.co.uk//htdocs/classroom/" local="132297299997287436" remote="132366771600000000" Dst="2" />
<file name="Daecca-Regular.css" server="ftp.fxprodesign.co.uk//htdocs/classroom/" local="132297299996948630" remote="132366771600000000" Dst="2" />
<file name="Daecca-Regular.html" server="ftp.fxprodesign.co.uk//htdocs/classroom/" local="132297299998136060" remote="132366771600000000" Dst="2" />
<file name="Daecca-Regular.woff" server="ftp.fxprodesign.co.uk//htdocs/classroom/" local="132297299999961176" remote="132366771600000000" Dst="2" />
<file name="Daecca-Regular.ttf" server="ftp.fxprodesign.co.uk//htdocs/classroom/" local="132297299999203211" remote="132366771600000000" Dst="2" />
<file name="Daecca-Regular.svg" server="ftp.fxprodesign.co.uk//htdocs/classroom/" local="132297299998794298" remote="132366771600000000" Dst="2" />
<file name="Daecca-Round.css" server="ftp.fxprodesign.co.uk//htdocs/classroom/" local="132297300000409972" remote="132366771600000000" Dst="2" />
<file name="Daecca-Round.eot" server="ftp.fxprodesign.co.uk//htdocs/classroom/" local="132297300000729131" remote="132366771600000000" Dst="2" />
<file name="Daecca-Round.html" server="ftp.fxprodesign.co.uk//htdocs/classroom/" local="132297300001098140" remote="132366771600000000" Dst="2" />
<file name="Daecca-Round.woff" server="ftp.fxprodesign.co.uk//htdocs/classroom/" local="132297300002185243" remote="132366771600000000" Dst="2" />
<file name="Daecca-Round.svg" server="ftp.fxprodesign.co.uk//htdocs/classroom/" local="132297300001566883" remote="132366771600000000" Dst="2" />
<file name="Daecca-Round.ttf" server="ftp.fxprodesign.co.uk//htdocs/classroom/" local="132297300001915968" remote="132366771600000000" Dst="2" />
<file name="Daecca-Bold.eot" server="ftp.4edu.co.uk//htdocs/" local="132297299993318045" remote="132367049400000000" Dst="2" />
<file name="Daecca-Bold.html" server="ftp.4edu.co.uk//htdocs/" local="132297299993627514" remote="132367049400000000" Dst="2" />
<file name="Daecca-Bold.css" server="ftp.4edu.co.uk//htdocs/" local="132297299992889209" remote="132367049400000000" Dst="2" />
<file name="Daecca-Bold.svg" server="ftp.4edu.co.uk//htdocs/" local="132297299994026176" remote="132367049400000000" Dst="2" />
<file name="Daecca-Bold.woff" server="ftp.4edu.co.uk//htdocs/" local="132297299994634819" remote="132367049400000000" Dst="2" />
<file name="Daecca-Bold.ttf" server="ftp.4edu.co.uk//htdocs/" local="132297299994365258" remote="132367049400000000" Dst="2" />
<file name="Daecca-Outline.css" server="ftp.4edu.co.uk//htdocs/" local="132297299994963802" remote="132367049400000000" Dst="2" />
<file name="Daecca-Outline.html" server="ftp.4edu.co.uk//htdocs/" local="132297299995611917" remote="132367049400000000" Dst="2" />
<file name="Daecca-Outline.eot" server="ftp.4edu.co.uk//htdocs/" local="132297299995303035" remote="132367049400000000" Dst="2" />
<file name="Daecca-Outline.woff" server="ftp.4edu.co.uk//htdocs/" local="132297299996639173" remote="132367049400000000" Dst="2" />
<file name="Daecca-Outline.ttf" server="ftp.4edu.co.uk//htdocs/" local="132297299996379884" remote="132367049400000000" Dst="2" />
<file name="Daecca-Outline.svg" server="ftp.4edu.co.uk//htdocs/" local="132297299996040770" remote="132367049400000000" Dst="2" />
<file name="Daecca-Regular.css" server="ftp.4edu.co.uk//htdocs/" local="132297299996948630" remote="132367049400000000" Dst="2" />
<file name="Daecca-Regular.html" server="ftp.4edu.co.uk//htdocs/" local="132297299998136060" remote="132367049400000000" Dst="2" />
<file name="Daecca-Regular.eot" server="ftp.4edu.co.uk//htdocs/" local="132297299997287436" remote="132367049400000000" Dst="2" />
<file name="Daecca-Regular.ttf" server="ftp.4edu.co.uk//htdocs/" local="132297299999203211" remote="132367049400000000" Dst="2" />
<file name="Daecca-Regular.woff" server="ftp.4edu.co.uk//htdocs/" local="132297299999961176" remote="132367049400000000" Dst="2" />
<file name="Daecca-Regular.svg" server="ftp.4edu.co.uk//htdocs/" local="132297299998794298" remote="132367049400000000" Dst="2" />
<file name="Daecca-Round.css" server="ftp.4edu.co.uk//htdocs/" local="132297300000409972" remote="132367049400000000" Dst="2" />
<file name="Daecca-Round.eot" server="ftp.4edu.co.uk//htdocs/" local="132297300000729131" remote="132367049400000000" Dst="2" />
<file name="Daecca-Round.html" server="ftp.4edu.co.uk//htdocs/" local="132297300001098140" remote="132367049400000000" Dst="2" />
<file name="Daecca-Round.woff" server="ftp.4edu.co.uk//htdocs/" local="132297300002185243" remote="132367049400000000" Dst="2" />
<file name="Daecca-Round.ttf" server="ftp.4edu.co.uk//htdocs/" local="132297300001915968" remote="132367049400000000" Dst="2" />
<file name="Daecca-Round.svg" server="ftp.4edu.co.uk//htdocs/" local="132297300001566883" remote="132367049400000000" Dst="2" />
<file name="Daecca-Bold.eot" server="ftp.marcuspalmerstudent.co.uk//htdocs/" local="132297299993318045" remote="132852559800000000" Dst="1" />
<file name="Daecca-Bold.css" server="ftp.marcuspalmerstudent.co.uk//htdocs/" local="132297299992889209" remote="132852559800000000" Dst="1" />
<file name="Daecca-Bold.html" server="ftp.marcuspalmerstudent.co.uk//htdocs/" local="132297299993627514" remote="132852559800000000" Dst="1" />
<file name="Daecca-Bold.svg" server="ftp.marcuspalmerstudent.co.uk//htdocs/" local="132297299994026176" remote="132852559800000000" Dst="1" />
<file name="Daecca-Bold.ttf" server="ftp.marcuspalmerstudent.co.uk//htdocs/" local="132297299994365258" remote="132852559800000000" Dst="1" />
<file name="Daecca-Bold.woff" server="ftp.marcuspalmerstudent.co.uk//htdocs/" local="132297299994634819" remote="132852559800000000" Dst="1" />
<file name="Daecca-Outline.css" server="ftp.marcuspalmerstudent.co.uk//htdocs/" local="132297299994963802" remote="132852559800000000" Dst="1" />
<file name="Daecca-Outline.eot" server="ftp.marcuspalmerstudent.co.uk//htdocs/" local="132297299995303035" remote="132852559800000000" Dst="1" />
<file name="Daecca-Outline.html" server="ftp.marcuspalmerstudent.co.uk//htdocs/" local="132297299995611917" remote="132852559800000000" Dst="1" />
<file name="Daecca-Outline.svg" server="ftp.marcuspalmerstudent.co.uk//htdocs/" local="132297299996040770" remote="132852559800000000" Dst="1" />
<file name="Daecca-Outline.ttf" server="ftp.marcuspalmerstudent.co.uk//htdocs/" local="132297299996379884" remote="132852559800000000" Dst="1" />
<file name="Daecca-Outline.woff" server="ftp.marcuspalmerstudent.co.uk//htdocs/" local="132297299996639173" remote="132852559800000000" Dst="1" />
<file name="Daecca-Regular.eot" server="ftp.marcuspalmerstudent.co.uk//htdocs/" local="132297299997287436" remote="132852559800000000" Dst="1" />
<file name="Daecca-Regular.html" server="ftp.marcuspalmerstudent.co.uk//htdocs/" local="132297299998136060" remote="132852559800000000" Dst="1" />
<file name="Daecca-Regular.css" server="ftp.marcuspalmerstudent.co.uk//htdocs/" local="132297299996948630" remote="132852559800000000" Dst="1" />
<file name="Daecca-Regular.svg" server="ftp.marcuspalmerstudent.co.uk//htdocs/" local="132297299998794298" remote="132852559800000000" Dst="1" />
<file name="Daecca-Regular.woff" server="ftp.marcuspalmerstudent.co.uk//htdocs/" local="132297299999961176" remote="132852559800000000" Dst="1" />
<file name="Daecca-Regular.ttf" server="ftp.marcuspalmerstudent.co.uk//htdocs/" local="132297299999203211" remote="132852559800000000" Dst="1" />
<file name="Daecca-Round.eot" server="ftp.marcuspalmerstudent.co.uk//htdocs/" local="132297300000729131" remote="132852559800000000" Dst="1" />
<file name="Daecca-Round.html" server="ftp.marcuspalmerstudent.co.uk//htdocs/" local="132297300001098140" remote="132852559800000000" Dst="1" />
<file name="Daecca-Round.css" server="ftp.marcuspalmerstudent.co.uk//htdocs/" local="132297300000409972" remote="132852559800000000" Dst="1" />
<file name="Daecca-Round.ttf" server="ftp.marcuspalmerstudent.co.uk//htdocs/" local="132297300001915968" remote="132852559800000000" Dst="1" />
<file name="Daecca-Round.woff" server="ftp.marcuspalmerstudent.co.uk//htdocs/" local="132297300002185243" remote="132852559800000000" Dst="1" />
<file name="Daecca-Round.svg" server="ftp.marcuspalmerstudent.co.uk//htdocs/" local="132297300001566883" remote="132852559800000000" Dst="1" />
</dwsync>