<?xml version="1.0" encoding="utf-8" ?>
<dwsync>
<file name="accordion-close.svg" server="ftp.marcuspalmerstudent.co.uk//htdocs/" local="132470604955154785" remote="132852572400000000" Dst="1" />
<file name="accordion-open.svg" server="ftp.marcuspalmerstudent.co.uk//htdocs/" local="132470604955154785" remote="132852573000000000" Dst="1" />
<file name="divider-icon.svg" server="ftp.marcuspalmerstudent.co.uk//htdocs/" local="132470604955164896" remote="132852573000000000" Dst="1" />
<file name="form-checkbox-indeterminate.svg" server="ftp.marcuspalmerstudent.co.uk//htdocs/" local="132470604955164896" remote="132852573000000000" Dst="1" />
<file name="form-checkbox.svg" server="ftp.marcuspalmerstudent.co.uk//htdocs/" local="132470604955173937" remote="132852573000000000" Dst="1" />
<file name="form-datalist.svg" server="ftp.marcuspalmerstudent.co.uk//htdocs/" local="132470604955173937" remote="132852573000000000" Dst="1" />
<file name="form-radio.svg" server="ftp.marcuspalmerstudent.co.uk//htdocs/" local="132470604955173937" remote="132852573000000000" Dst="1" />
<file name="form-select.svg" server="ftp.marcuspalmerstudent.co.uk//htdocs/" local="132470604955183929" remote="132852573000000000" Dst="1" />
<file name="list-bullet.svg" server="ftp.marcuspalmerstudent.co.uk//htdocs/" local="132470604955183929" remote="132852573000000000" Dst="1" />
<file name="nav-parent-close.svg" server="ftp.marcuspalmerstudent.co.uk//htdocs/" local="132470604955183929" remote="132852573000000000" Dst="1" />
<file name="nav-parent-open.svg" server="ftp.marcuspalmerstudent.co.uk//htdocs/" local="132470604955193906" remote="132852573000000000" Dst="1" />
</dwsync>